sensorvision/__init__.py
sensorvision/auth.py
sensorvision/client.py
sensorvision/exceptions.py
sensorvision/models.py
sensorvision/utils.py
sensorvision_sdk-0.1.1.dist-info/licenses/LICENSE
sensorvision_sdk-0.1.1.dist-info/METADATA
sensorvision_sdk-0.1.1.dist-info/WHEEL
sensorvision_sdk-0.1.1.dist-info/top_level.txt
sensorvision_sdk-0.1.1.dist-info/RECORD
