Metadata-Version: 2.4
Name: sensorvision-sdk
Version: 0.1.1
Summary: Python SDK for SensorVision IoT platform
Home-page: https://github.com/CodeFleck/sensorvision
Author: SensorVision Team
Author-email: SensorVision Team <support@sensorvision.io>
License: MIT
Project-URL: Homepage, https://github.com/CodeFleck/sensorvision
Project-URL: Documentation, https://github.com/CodeFleck/sensorvision/wiki
Project-URL: Repository, https://github.com/CodeFleck/sensorvision
Project-URL: Bug Tracker, https://github.com/CodeFleck/sensorvision/issues
Keywords: iot,telemetry,monitoring,sensor,raspberry-pi,esp32
Classifier: Development Status :: 4 - Beta
Classifier: Intended Audience :: Developers
Classifier: Topic :: Software Development :: Libraries :: Python Modules
Classifier: Topic :: System :: Monitoring
Classifier: Topic :: System :: Hardware
Classifier: License :: OSI Approved :: MIT License
Classifier: Programming Language :: Python :: 3
Classifier: Programming Language :: Python :: 3.8
Classifier: Programming Language :: Python :: 3.9
Classifier: Programming Language :: Python :: 3.10
Classifier: Programming Language :: Python :: 3.11
Classifier: Programming Language :: Python :: 3.12
Requires-Python: >=3.8
License-File: LICENSE
Requires-Dist: requests>=2.25.0
Provides-Extra: async
Requires-Dist: aiohttp>=3.8.0; extra == "async"
Provides-Extra: dev
Requires-Dist: pytest>=7.0.0; extra == "dev"
Requires-Dist: pytest-asyncio>=0.21.0; extra == "dev"
Requires-Dist: pytest-cov>=4.0.0; extra == "dev"
Requires-Dist: mypy>=1.0.0; extra == "dev"
Requires-Dist: black>=23.0.0; extra == "dev"
Requires-Dist: flake8>=6.0.0; extra == "dev"
Requires-Dist: isort>=5.12.0; extra == "dev"
Provides-Extra: raspberry-pi
Requires-Dist: Adafruit-DHT>=1.4.0; extra == "raspberry-pi"
Dynamic: author
Dynamic: home-page
Dynamic: license-file
Dynamic: requires-python
